pyaccessors/__init__.py
pyaccessors-0.0.5.dist-info/LICENSE
pyaccessors-0.0.5.dist-info/METADATA
pyaccessors-0.0.5.dist-info/WHEEL
pyaccessors-0.0.5.dist-info/top_level.txt
pyaccessors-0.0.5.dist-info/RECORD
