Metadata-Version: 2.1
Name: pyaccessors
Version: 0.0.5
Summary: Access lists of dictionaries with their keys' values
Home-page: https://github.com/hypostulate/pyaccessors
Author: David Born
Author-email: laggs0@gmail.com
License: UNKNOWN
Platform: UNKNOWN
Classifier: Programming Language :: Python :: 3
Classifier: License :: OSI Approved :: MIT License
Classifier: Operating System :: OS Independent
Requires-Python: >=3.6
